github_actions_ai_analyzer/__init__.py
github_actions_ai_analyzer/cli/__init__.py
github_actions_ai_analyzer/cli/main.py
github_actions_ai_analyzer/core/__init__.py
github_actions_ai_analyzer/core/ai_prompt_optimizer.py
github_actions_ai_analyzer/core/analyzer.py
github_actions_ai_analyzer/core/context_collector.py
github_actions_ai_analyzer/core/log_processor.py
github_actions_ai_analyzer/core/pattern_matcher.py
github_actions_ai_analyzer/types/__init__.py
github_actions_ai_analyzer/types/analysis_types.py
github_actions_ai_analyzer/types/context_types.py
github_actions_ai_analyzer/types/log_types.py
github_actions_ai_analyzer/types/pattern_types.py
github_actions_ai_analyzer-0.1.7.dist-info/licenses/LICENSE
github_actions_ai_analyzer-0.1.7.dist-info/METADATA
github_actions_ai_analyzer-0.1.7.dist-info/WHEEL
github_actions_ai_analyzer-0.1.7.dist-info/entry_points.txt
github_actions_ai_analyzer-0.1.7.dist-info/top_level.txt
github_actions_ai_analyzer-0.1.7.dist-info/RECORD
