Metadata-Version: 2.4
Name: github-actions-ai-analyzer
Version: 0.1.7
Summary: GitHub Actionsのエラーログを解析し、AIによる改善案生成と品質向上を支援するライブラリ
Author-email: Scott LZ <scottlz0310@gmail.com>
Maintainer-email: Scott LZ <scottlz0310@gmail.com>
License: MIT
Project-URL: Homepage, https://github.com/scottlz0310/Github-Actions-AI-Analyzer
Project-URL: Repository, https://github.com/scottlz0310/Github-Actions-AI-Analyzer
Project-URL: Documentation, https://github.com/scottlz0310/Github-Actions-AI-Analyzer#readme
Project-URL: Issues, https://github.com/scottlz0310/Github-Actions-AI-Analyzer/issues
Keywords: github-actions,ci-cd,error-analysis,ai,automation,logging,debugging,devops,quality-improvement,ai-quality,continuous-improvement
Classifier: Development Status :: 4 - Beta
Classifier: Intended Audience :: Developers
Classifier: Intended Audience :: System Administrators
Classifier: License :: OSI Approved :: MIT License
Classifier: Operating System :: OS Independent
Classifier: Programming Language :: Python :: 3
Classifier: Programming Language :: Python :: 3.8
Classifier: Programming Language :: Python :: 3.9
Classifier: Programming Language :: Python :: 3.10
Classifier: Programming Language :: Python :: 3.11
Classifier: Programming Language :: Python :: 3.12
Classifier: Topic :: Software Development :: Libraries :: Python Modules
Classifier: Topic :: Software Development :: Quality Assurance
Classifier: Topic :: Software Development :: Testing
Classifier: Topic :: System :: Logging
Classifier: Topic :: System :: Monitoring
Classifier: Topic :: Utilities
Classifier: Typing :: Typed
Requires-Python: >=3.8
License-File: LICENSE
Requires-Dist: pyyaml>=6.0
Requires-Dist: requests>=2.28.0
Requires-Dist: click>=8.0.0
Requires-Dist: rich>=12.0.0
Requires-Dist: pydantic>=2.0.0
Requires-Dist: regex>=2022.0.0
Requires-Dist: jinja2>=3.0.0
Provides-Extra: dev
Requires-Dist: pytest>=7.0.0; extra == "dev"
Requires-Dist: pytest-cov>=4.0.0; extra == "dev"
Requires-Dist: pytest-benchmark>=4.0.0; extra == "dev"
Requires-Dist: black>=22.0.0; extra == "dev"
Requires-Dist: isort>=5.0.0; extra == "dev"
Requires-Dist: flake8>=5.0.0; extra == "dev"
Requires-Dist: mypy>=1.0.0; extra == "dev"
Requires-Dist: types-PyYAML>=6.0.0; extra == "dev"
Requires-Dist: pre-commit>=2.0.0; extra == "dev"
Requires-Dist: bandit>=1.7.0; extra == "dev"
Requires-Dist: safety>=2.0.0; extra == "dev"
Requires-Dist: pip-tools>=7.0.0; extra == "dev"
Requires-Dist: twine>=4.0.0; extra == "dev"
Requires-Dist: build>=0.10.0; extra == "dev"
Requires-Dist: commitizen>=3.0.0; extra == "dev"
Provides-Extra: ai-quality
Requires-Dist: pytest>=7.0.0; extra == "ai-quality"
Requires-Dist: pytest-cov>=4.0.0; extra == "ai-quality"
Requires-Dist: flake8>=6.0.0; extra == "ai-quality"
Requires-Dist: black>=23.0.0; extra == "ai-quality"
Requires-Dist: isort>=5.12.0; extra == "ai-quality"
Requires-Dist: mypy>=1.0.0; extra == "ai-quality"
Requires-Dist: types-PyYAML>=6.0.0; extra == "ai-quality"
Dynamic: license-file
